{
  "fixtures": [
    {
      "match": {
        "endpoint": "fal",
        "userMessage": "Handheld camera tracks forward alongside Scarlett walking at a relaxed pace along the weathered wooden promenade boards with natural stride momentum. Turquoise swells roll in the background as surfers rise on breaking waves. She turns her head and glances back over her shoulder toward the camera with effortless poise.\n\nScarlett delivers her line with effortless breezy tone, lips moving naturally while her body maintains forward momentum and her gaze briefly connects with the lens.\n\nSalt breeze lifts fabric edges and loose strands while foam-tipped waves crest behind her under bright morning coastal light.\n\n[SCARLETT, effortless breezy]: \"Made for the water. Wear it everywhere.\"\n\nAmbient sounds: ocean waves rolling, distant surfer calls, light coastal breeze. wooden board footsteps, gentle fabric rustle in breeze.",
        "model": "fal-ai/kling-video/v3/pro/image-to-video",
        "turnIndex": 0,
        "hasToolResult": false
      },
      "response": {
        "json": {
          "video": {
            "url": "https://v3b.fal.media/files/b/0a9a3e39/mv5jKcXQvC3KDYwdWWErL_output.mp4",
            "content_type": "video/mp4",
            "file_name": "output.mp4",
            "file_size": 22903634
          }
        },
        "status": 200
      }
    }
  ]
}
