{
  "fixtures": [
    {
      "match": {
        "endpoint": "fal",
        "userMessage": "Handheld camera drifts slowly inward from medium framing toward Scarlett seated at the white vanity, capturing her hand lifting the coral lipstick from its open packaging and turning the bullet deliberately between her fingers to catch the directional window light.\nHer soft reflective voiceover line accompanies the slow rotation with minimal mouth movement and focused, unhurried gestures.\nSubtle fabric shifts at her wrist and faint dust motes drift in the bright air as the shot tightens on the product.\n\n[SCARLETT, soft reflective]: \"One shade. One summer.\"\n\nAmbient sounds: quiet Bondi studio room tone with soft natural light ambience. soft lipstick case handling, light fingernail trace on matte surface.",
        "model": "fal-ai/kling-video/v3/pro/image-to-video",
        "turnIndex": 0,
        "hasToolResult": false
      },
      "response": {
        "json": {
          "video": {
            "url": "https://v3b.fal.media/files/b/0a9a2b82/ZZY9Mxb3ePBxV5xY9ecHu_output.mp4",
            "content_type": "video/mp4",
            "file_name": "output.mp4",
            "file_size": 9733003
          }
        },
        "status": 200
      }
    }
  ]
}
